{
  "minecraft:recipes/transportation/acacia_boat": {
    "criteria": {
      "entered_water": "2022-10-31 14:47:25 -0700"
    },
    "done": true
  },
  "minecraft:recipes/misc/bone_meal_from_bone": {
    "criteria": {
      "has_bone": "2022-10-31 14:48:53 -0700"
    },
    "done": true
  },
  "minecraft:recipes/building_blocks/snow": {
    "criteria": {
      "has_snowball": "2022-10-31 14:51:45 -0700"
    },
    "done": true
  },
  "minecraft:recipes/transportation/dark_oak_boat": {
    "criteria": {
      "entered_water": "2022-10-31 14:47:25 -0700"
    },
    "done": true
  },
  "minecraft:story/shiny_gear": {
    "criteria": {
      "diamond_helmet": "2022-10-31 14:47:09 -0700"
    },
    "done": true
  },
  "minecraft:adventure/root": {
    "criteria": {
      "killed_by_something": "2022-10-31 14:48:06 -0700"
    },
    "done": true
  },
  "minecraft:recipes/transportation/birch_boat": {
    "criteria": {
      "entered_water": "2022-10-31 14:47:25 -0700"
    },
    "done": true
  },
  "minecraft:recipes/transportation/boat": {
    "criteria": {
      "entered_water": "2022-10-31 14:47:25 -0700"
    },
    "done": true
  },
  "minecraft:recipes/transportation/jungle_boat": {
    "criteria": {
      "entered_water": "2022-10-31 14:47:25 -0700"
    },
    "done": true
  },
  "minecraft:recipes/transportation/spruce_boat": {
    "criteria": {
      "entered_water": "2022-10-31 14:47:25 -0700"
    },
    "done": true
  },
  "minecraft:recipes/decorations/snow_layer": {
    "criteria": {
      "has_snowball": "2022-10-31 14:51:45 -0700"
    },
    "done": true
  },
  "minecraft:adventure/adventuring_time": {
    "criteria": {
      "forest": "2022-10-31 14:46:51 -0700",
      "beaches": "2022-10-31 14:47:22 -0700"
    },
    "done": false
  }
}